src/__init__.py
src/server.py
src/version.py
src/clients/__init__.py
src/clients/base.py
src/clients/exceptions.py
src/clients/common/__init__.py
src/clients/common/alias.py
src/clients/common/client.py
src/clients/common/cluster.py
src/clients/common/document.py
src/clients/common/general.py
src/clients/common/index.py
src/tools/__init__.py
src/tools/alias.py
src/tools/cluster.py
src/tools/document.py
src/tools/general.py
src/tools/index.py
src/tools/register.py
mseep_elasticsearch_mcp_server-2.0.12.dist-info/METADATA
mseep_elasticsearch_mcp_server-2.0.12.dist-info/WHEEL
mseep_elasticsearch_mcp_server-2.0.12.dist-info/entry_points.txt
mseep_elasticsearch_mcp_server-2.0.12.dist-info/licenses/LICENSE
mseep_elasticsearch_mcp_server-2.0.12.dist-info/RECORD
