Metadata-Version: 2.4
Name: mseep-elasticsearch-mcp-server
Version: 2.0.12
Summary: MCP Server for interacting with Elasticsearch and OpenSearch
Author-email: mseep <support@skydeck.ai>
License:                                  Apache License
License-File: LICENSE
Requires-Python: >=3.10
Requires-Dist: anthropic==0.49.0
Requires-Dist: elasticsearch==8.17.2
Requires-Dist: fastmcp==2.8.0
Requires-Dist: mcp==1.9.2
Requires-Dist: opensearch-py==2.8.0
Requires-Dist: python-dotenv==1.1.0
Requires-Dist: tomli-w==1.2.0
Requires-Dist: tomli==2.2.1
